pystats.pyd
PyStats-0.1.2.dist-info/LICENSE
PyStats-0.1.2.dist-info/METADATA
PyStats-0.1.2.dist-info/WHEEL
PyStats-0.1.2.dist-info/top_level.txt
PyStats-0.1.2.dist-info/RECORD
