Metadata-Version: 2.1
Name: PyStats
Version: 0.1.2
Summary: A Python 3 package of statistical analysis and distributions
Home-page: https://github.com/marcizhu/PyStats
Author: Marc Izquierdo
Author-email: marcizhu@gmail.com
Project-URL: Bug Tracker, https://github.com/marcizhu/PyStats/issues
Project-URL: Documentation, https://pystats.readthedocs.org
Classifier: Development Status :: 4 - Beta
Classifier: Natural Language :: English
Classifier: Programming Language :: C++
Classifier: License :: OSI Approved :: MIT License
Classifier: Operating System :: OS Independent
License-File: LICENSE
